mllibprodest/__init__.py
mllibprodest/interfaces.py
mllibprodest/provider.py
mllibprodest/shared_classes.py
mllibprodest/utils.py
mllibprodest/initiators/__init__.py
mllibprodest/initiators/model_initiator.py
mllibprodest/providers_types/__init__.py
mllibprodest/providers_types/local_provider.py
mllibprodest/providers_types/minio_provider.py
mllibprodest/providers_types/mlflow_provider.py
mllibprodest/providers_types/utils.py
mllibprodest/validators/__init__.py
mllibprodest/validators/test.py
mllibprodest-1.8.10.dist-info/licenses/LICENSE
mllibprodest-1.8.10.dist-info/METADATA
mllibprodest-1.8.10.dist-info/WHEEL
mllibprodest-1.8.10.dist-info/top_level.txt
mllibprodest-1.8.10.dist-info/RECORD
