Metadata-Version: 2.4
Name: mllibprodest
Version: 1.8.10
Summary: Biblioteca de Machine Learning (ML) do Prodest.
Home-page: https://github.com/prodest/mllibprodest
Author: Instituto de Tecnologia da Informação e Comunicação do Espírito Santo (PRODEST)
Author-email: "Instituto de Tecnologia da Informação e Comunicação do Espírito Santo (PRODEST)" <prodest@prodest.es.gov.br>
License-Expression: GPL-3.0-or-later
Project-URL: Homepage, https://github.com/prodest/mllibprodest
Project-URL: Bug Tracker, https://github.com/prodest/mllibprodest/issues
Project-URL: Documentation, https://prodest.github.io/mllibprodest
Keywords: Prodest,ML,lib,stack
Classifier: Programming Language :: Python :: 3.12
Classifier: Operating System :: OS Independent
Classifier: Intended Audience :: Developers
Classifier: Natural Language :: Portuguese (Brazilian)
Requires-Python: >=3.12
License-File: LICENSE
Requires-Dist: minio==7.2.18
Requires-Dist: python-dotenv==1.1.1
Requires-Dist: mlflow==3.4.0
Requires-Dist: boto3==1.40.43
Dynamic: license-file
